dumme/__init__.py
dumme/dumme.py
dumme/utils.py
dumme/viz.py
DumME-0.1.0.dist-info/LICENSE
DumME-0.1.0.dist-info/METADATA
DumME-0.1.0.dist-info/WHEEL
DumME-0.1.0.dist-info/top_level.txt
DumME-0.1.0.dist-info/RECORD
