Metadata-Version: 2.1
Name: DumME
Version: 0.1.0
Summary: Mixed Effects Dummy Model
Author-email: "Peter Kalverla." <p.kalverla@esciencecenter.nl>, "Stefan Verhoeven." <s.verhoeven@esciencecenter.nl>
Project-URL: Repository, https://github.com/phenology/dumme
Project-URL: Original, https://github.com/manifoldai/merf
Keywords: random forest,machine learning,mixed effects
Classifier: Development Status :: 3 - Alpha
Classifier: License :: OSI Approved :: MIT License
Classifier: Programming Language :: Python :: 3
Classifier: Topic :: Scientific/Engineering :: Artificial Intelligence
Requires-Python: >=3.9
License-File: LICENSE
Requires-Dist: pandas >=1.0
Requires-Dist: numpy >=1.20
Requires-Dist: scikit-learn
Requires-Dist: matplotlib >=3.0
Requires-Dist: lightgbm
Provides-Extra: dev
Requires-Dist: black ; extra == 'dev'
Requires-Dist: ruff ; extra == 'dev'
Requires-Dist: isort ; extra == 'dev'
Requires-Dist: pytest ; extra == 'dev'
Requires-Dist: pycaret ; extra == 'dev'
